{
  "portfolios": [
    {
      "name": "Avadhut Sathe",
      "company": "PaaramiDigital",
      "image": "img/asta.png",
      "website": "https://www.avadhutsathe.com/"
    },
    {
      "name": "UFO Moviez",
      "company": "PaaramiDigital",
      "image": "img/ufo.png",
      "website": "https://ufomoviez.com"
    },
    {
      "name": "Clinico",
      "company": "PaaramiDigital",
      "image": "img/clinico.png",
      "website": "https://www.clinico.in"
    },
    {
      "name": "BesameWellness",
      "company": "PaaramiDigital",
      "image": "img/besame.png",
      "website": "https://www.besamewellness.com"
    },
    {
      "name": "FVC",
      "company": "PaaramiDigital",
      "image": "img/fvc.png",
      "website": "https://www.fvc.com"
    },
    {
      "name": "Moviebeam",
      "company": "PaaramiDigital",
      "image": "img/movie.png",
      "website": "https://www.moviebeam.com"
    },
    {
      "name": "Mohempic",
      "company": "PaaramiDigital",
      "image": "img/mohem.png",
      "website": "https://mohempic.com/"
    },
    {
      "name": "Mindfield",
      "company": "PaaramiDigital",
      "image": "img/mind.png",
      "website": "https://www.mindfieldresources.com/"
    },
    {
      "name": "GTLInfra",
      "company": "PaaramiDigital",
      "image": "img/gtl.png",
      "website": "https://www.gtlinfra.com/"
    },
    {
      "name": "AnssiWellness",
      "company": "PaaramiDigital",
      "image": "img/anssi.png",
      "website": "https://www.anssiwellness.com"
    },
    {
      "name": "Periyar Gaushala",
      "company": "PaaramiDigital",
      "image": "img/periyar.png",
      "website": "https://www.periyargaushala.com"
    },
    {
      "name": "ActionAgainstHunger",
      "company": "CreativeWebo",
      "image": "img/aah.png",
      "website": "https://actionagainsthunger.in"
    },
    {
      "name": "GPK logistech",
      "image": "img/gpk.png",
      "website": "https://www.gpklogistech.com/"
    },
    {
      "name": "Zufr",
      "image": "img/zufr.png",
      "website": "https://simpfytech.com.au/"
    },
    {
      "image": "img/asta.png",
      "name": "Avadhut Sathe LandingPage",
      "company": "PaaramiDigital",
      "website": "https://eo.avadhutsathe.com/"
    },
    {
      "image": "img/aanvi.png",
      "name": "AanviHearing LandingPage",
      "company": "PaaramiDigital",
      "website": "http://care.aanviihearing.com/"
    },
    {
      "image": "img/trading.png",
      "name": "TradingStyle LandingPage",
      "company": "PaaramiDigital",
      "website": "https://www.tradingstyle.in/webinar-2022"
    },
    {
      "name": "EcoKari",
      "image": "img/ecokari.png",
      "website": "https://ecokari.com"
    },
    {
      "name": "LuminousPretty",
      "image": "img/lum.png",
      "website": "https://www.luminouspretties.co.uk"
    },
    {
      "name": "RBS Intellect",
      "image": "img/rbs.png",
      "website": "https://rbsintellect.com"
    },
    {
      "name": "Watchyourhealth",
      "image": "img/wyh.png",
      "website": "https://www.watchyourhealth.com"
    },
    {
      "name": "Watchyourhealth Dubai website",
      "image": "img/wyh.png",
      "website": "https://www.watchyourhealth.com/du"
    },
    {
      "image": "img/wyh.png",
      "name": "WYH Presentation",
      "company": "WatchYourHealth",
      "website": "https://presentation.watchyourhealth.com/"
    },
    {
      "name": "Feel To Print",
      "image": "img/f2p.png",
      "website": "https://feeltoprint.com"
    },
    {
      "name": "Aditech Solutions",
      "image": "img/adit.png",
      "website": "https://aditechsoftwares.com"
    },
    {
      "image": "img/madhav.png",
      "name": "Madhavprash Store",
      "company": "WatchYourHealth",
      "website": "https://www.madhavprash.store"
    },
    {
      "image": "img/funky.png",
      "name": "Funky Crabs",
      "website": "https://www.funkycrabs.com"
    }
  ]
}